matrixflow/__init__.py
matrixflow/matrix.py
matrixflow/utils.py
matrixflow/vector.py
matrixflow-0.1.5.dist-info/licenses/LICENSE
matrixflow-0.1.5.dist-info/METADATA
matrixflow-0.1.5.dist-info/WHEEL
matrixflow-0.1.5.dist-info/top_level.txt
matrixflow-0.1.5.dist-info/RECORD
