Metadata-Version: 2.4
Name: matrixflow
Version: 0.1.5
Summary: A rich library with implementations for mathematical matrices and vectors and their operations
Author-email: Tom-the-Bomb <me@tomthebomb.dev>
Project-URL: documentation, https://matrixflow.readthedocs.io/en/latest/
Project-URL: homepage, https://github.com/Tom-the-Bomb/matrixflow
Project-URL: repository, https://github.com/Tom-the-Bomb/matrixflow
Project-URL: Issue tracker, https://github.com/Tom-the-Bomb/matrixflow/issues/
Keywords: vector,matrix,math
Classifier: Programming Language :: Python :: 3.10
Classifier: Programming Language :: Python :: 3.11
Classifier: Programming Language :: Python :: 3.12
Classifier: Natural Language :: English
Classifier: Intended Audience :: Developers
Classifier: Topic :: Scientific/Engineering :: Mathematics
Classifier: Operating System :: OS Independent
Classifier: Topic :: Software Development :: Libraries
Classifier: Topic :: Software Development :: Libraries :: Python Modules
Classifier: Typing :: Typed
Requires-Python: >=3.10
License-File: LICENSE
Provides-Extra: docs
Requires-Dist: sphinx; extra == "docs"
Requires-Dist: furo; extra == "docs"
Requires-Dist: sphinxext-opengraph; extra == "docs"
Requires-Dist: sphinx-copybutton; extra == "docs"
Provides-Extra: dev
Requires-Dist: twine; extra == "dev"
Requires-Dist: build; extra == "dev"
Dynamic: license-file
